[{"area":15,"price":20.0,"name":"SPECIALFLAT","coordinates":{"x":5.0,"y":10},"numberOfRooms":2,"livingSpace":15,"id":0,"transport":"FEW","house":{"numberOfLifts":2,"numberOfFloors":10,"year":15,"name":"house1","numberOfFlatsOnFloor":15}},{"area":15,"price":20.0,"name":"flat2","coordinates":{"x":5.0,"y":10},"numberOfRooms":2,"livingSpace":15,"id":1,"transport":"FEW","house":{"numberOfLifts":2,"numberOfFloors":10,"year":15,"name":"house1","numberOfFlatsOnFloor":15}},{"area":15,"price":20.0,"name":"flat3","coordinates":{"x":5.0,"y":10},"numberOfRooms":2,"livingSpace":15,"id":2,"transport":"FEW","house":{"numberOfLifts":2,"numberOfFloors":10,"year":15,"name":"house1","numberOfFlatsOnFloor":15}},{"area":800,"price":100.0,"name":"antoha","coordinates":{"x":15.0,"y":20},"numberOfRooms":2,"livingSpace":100,"id":3,"transport":"NORMAL","house":{"numberOfLifts":2,"numberOfFloors":5,"year":1999,"name":"anthahouse","numberOfFlatsOnFloor":20}}]